fixme/__init__.py
fixme/__main__.py
fixme/api.py
fixme/cli.py
fixme/console.py
fixme/session.py
fixme/utils.py
fixme/prompts/__init__.py
fixme/prompts/diagnose_issue.py
fixme/prompts/fix_patch.py
fixme/prompts/gather_information.py
fixme/prompts/generate_patch.py
fixme/prompts/helpers.py
fixme-0.4.dist-info/LICENSE
fixme-0.4.dist-info/METADATA
fixme-0.4.dist-info/WHEEL
fixme-0.4.dist-info/entry_points.txt
fixme-0.4.dist-info/top_level.txt
fixme-0.4.dist-info/RECORD
