Metadata-Version: 2.1
Name: fixme
Version: 0.4
Summary: Use AI to automatically fix bugs
Home-page: https://github.com/helloworld/fixme
Author: helloworld
License: Apache License, Version 2.0
Project-URL: Issues, https://github.com/helloworld/fixme/issues
Project-URL: CI, https://github.com/helloworld/fixme/actions
Project-URL: Changelog, https://github.com/helloworld/fixme/releases
Requires-Python: >=3.7
License-File: LICENSE
Requires-Dist: click
Requires-Dist: openai
Requires-Dist: rich
Requires-Dist: pydantic
Provides-Extra: black
Requires-Dist: black ; extra == 'black'
Provides-Extra: pyright
Requires-Dist: pyright ; extra == 'pyright'
Provides-Extra: ruff
Requires-Dist: ruff ; extra == 'ruff'
Provides-Extra: test
Requires-Dist: pytest ; extra == 'test'
